README
setup.py
aweber/__init__.py
aweber/defaults.py
aweber/forms.py
aweber/models.py
aweber/signals.py
aweber/testsettings.py
aweber/urls.py
aweber/utils.py
aweber/views.py
django_aweber.egg-info/PKG-INFO
django_aweber.egg-info/SOURCES.txt
django_aweber.egg-info/dependency_links.txt
django_aweber.egg-info/requires.txt
django_aweber.egg-info/top_level.txt