Metadata-Version: 1.1
Name: django-aweber
Version: 0.3
Summary: An Aweber based user-signup application for Django
Home-page: http://github.com/un33k/django-aweber
Author: Val Neekman
Author-email: val@neekware.com
License: UNKNOWN
Platform: UNKNOWN
Classifier: Development Status :: 4 - Beta
Classifier: Environment :: Web Environment
Classifier: Intended Audience :: Developers
Classifier: License :: OSI Approved :: BSD License
Classifier: Operating System :: OS Independent
Classifier: Programming Language :: Python
Classifier: Topic :: Utilities
